glypniro/__init__.py
glypniro/cli.py
glypniro/common.py
glypniro/reformat.py
glypniro/reformat_skyline.py
glypniro-0.1.8.dist-info/entry_points.txt
glypniro-0.1.8.dist-info/LICENSE
glypniro-0.1.8.dist-info/METADATA
glypniro-0.1.8.dist-info/WHEEL
glypniro-0.1.8.dist-info/RECORD
