Metadata-Version: 2.1
Name: glypniro
Version: 0.1.8
Summary: A automated script for processing and combining Byonic and PD standard output.
Author: Toan Phung
Author-email: toan.phungkhoiquoctoan@gmail.com
Requires-Python: >=3.9,<3.13
Classifier: Programming Language :: Python :: 3
Classifier: Programming Language :: Python :: 3.9
Classifier: Programming Language :: Python :: 3.10
Classifier: Programming Language :: Python :: 3.11
Classifier: Programming Language :: Python :: 3.12
Requires-Dist: click (>=8.1.6,<9.0.0)
Requires-Dist: openpyxl (>=3.1.2,<4.0.0)
Requires-Dist: pandas (>=2.0.3,<3.0.0)
Requires-Dist: scipy (>=1.11.1,<2.0.0)
Requires-Dist: sequal (>=1.0.2,<2.0.0)
Requires-Dist: uniprotparser (>=1.1.0,<2.0.0)
Requires-Dist: xlrd (>=2.0.1,<3.0.0)
